[
  {
    "id": 1,
    "referenceNumber": "MPBUDGE-ZAMSTATS-2024-001",
    "entity": "Zambia Statistics Agency",
    "date": "2024-09-06T00:00:00Z",
    "description": "Mp Budget Analysis entry 1 for Zambia Statistics Agency",
    "amount": 11833429.43,
    "currency": "ZMW",
    "status": "Active",
    "preparedBy": "Florence Daka",
    "approvedBy": "Samuel Mutale",
    "remarks": "Standard mp-budget-analysis record for Zambia Statistics Agency"
  },
  {
    "id": 2,
    "referenceNumber": "MPBUDGE-ZAMSTATS-2024-002",
    "entity": "Zambia Statistics Agency",
    "date": "2024-12-03T00:00:00Z",
    "description": "Mp Budget Analysis entry 2 for Zambia Statistics Agency",
    "amount": 44426852.0,
    "currency": "ZMW",
    "status": "Completed",
    "preparedBy": "Christine Malama",
    "approvedBy": "Joseph Phiri",
    "remarks": "Standard mp-budget-analysis record for Zambia Statistics Agency"
  },
  {
    "id": 3,
    "referenceNumber": "MPBUDGE-ZAMSTATS-2024-003",
    "entity": "Zambia Statistics Agency",
    "date": "2024-08-19T00:00:00Z",
    "description": "Mp Budget Analysis entry 3 for Zambia Statistics Agency",
    "amount": 29737377.15,
    "currency": "ZMW",
    "status": "Approved",
    "preparedBy": "David Bwalya",
    "approvedBy": "Emmanuel Simukonda",
    "remarks": "Standard mp-budget-analysis record for Zambia Statistics Agency"
  },
  {
    "id": 4,
    "referenceNumber": "MPBUDGE-ZAMSTATS-2024-004",
    "entity": "Zambia Statistics Agency",
    "date": "2024-07-26T00:00:00Z",
    "description": "Mp Budget Analysis entry 4 for Zambia Statistics Agency",
    "amount": 42270981.57,
    "currency": "ZMW",
    "status": "Completed",
    "preparedBy": "Charity Mwale",
    "approvedBy": "Esther Banda",
    "remarks": "Standard mp-budget-analysis record for Zambia Statistics Agency"
  },
  {
    "id": 5,
    "referenceNumber": "MPBUDGE-ZAMSTATS-2024-005",
    "entity": "Zambia Statistics Agency",
    "date": "2024-02-26T00:00:00Z",
    "description": "Mp Budget Analysis entry 5 for Zambia Statistics Agency",
    "amount": 37238232.91,
    "currency": "ZMW",
    "status": "Approved",
    "preparedBy": "Andrew Ngoma",
    "approvedBy": "Robert Nkonde",
    "remarks": "Standard mp-budget-analysis record for Zambia Statistics Agency"
  },
  {
    "id": 6,
    "referenceNumber": "MPBUDGE-ZAMSTATS-2024-006",
    "entity": "Zambia Statistics Agency",
    "date": "2024-03-06T00:00:00Z",
    "description": "Mp Budget Analysis entry 6 for Zambia Statistics Agency",
    "amount": 26420744.35,
    "currency": "ZMW",
    "status": "Active",
    "preparedBy": "Miriam Mbewe",
    "approvedBy": "Miriam Nakambwe",
    "remarks": "Standard mp-budget-analysis record for Zambia Statistics Agency"
  },
  {
    "id": 7,
    "referenceNumber": "MPBUDGE-ZAMSTATS-2024-007",
    "entity": "Zambia Statistics Agency",
    "date": "2024-09-04T00:00:00Z",
    "description": "Mp Budget Analysis entry 7 for Zambia Statistics Agency",
    "amount": 39179115.13,
    "currency": "ZMW",
    "status": "Active",
    "preparedBy": "Robert Mwanza",
    "approvedBy": "Joseph Chilufya",
    "remarks": "Standard mp-budget-analysis record for Zambia Statistics Agency"
  },
  {
    "id": 8,
    "referenceNumber": "MPBUDGE-ZAMSTATS-2024-008",
    "entity": "Zambia Statistics Agency",
    "date": "2024-02-06T00:00:00Z",
    "description": "Mp Budget Analysis entry 8 for Zambia Statistics Agency",
    "amount": 9738061.87,
    "currency": "ZMW",
    "status": "Pending",
    "preparedBy": "Peter Mwanza",
    "approvedBy": "Patricia Ngoma",
    "remarks": "Standard mp-budget-analysis record for Zambia Statistics Agency"
  },
  {
    "id": 9,
    "referenceNumber": "MPBUDGE-ZAMSTATS-2024-009",
    "entity": "Zambia Statistics Agency",
    "date": "2024-11-22T00:00:00Z",
    "description": "Mp Budget Analysis entry 9 for Zambia Statistics Agency",
    "amount": 8658677.97,
    "currency": "ZMW",
    "status": "Completed",
    "preparedBy": "Andrew Chipimo",
    "approvedBy": "Joseph Simukonda",
    "remarks": "Standard mp-budget-analysis record for Zambia Statistics Agency"
  },
  {
    "id": 10,
    "referenceNumber": "MPBUDGE-ZAMSTATS-2024-010",
    "entity": "Zambia Statistics Agency",
    "date": "2024-10-25T00:00:00Z",
    "description": "Mp Budget Analysis entry 10 for Zambia Statistics Agency",
    "amount": 9194065.01,
    "currency": "ZMW",
    "status": "Approved",
    "preparedBy": "Miriam Simwanza",
    "approvedBy": "Joseph Chipimo",
    "remarks": "Standard mp-budget-analysis record for Zambia Statistics Agency"
  },
  {
    "id": 11,
    "referenceNumber": "MPBUDGE-ZAMSTATS-2024-011",
    "entity": "Zambia Statistics Agency",
    "date": "2024-08-17T00:00:00Z",
    "description": "Mp Budget Analysis entry 11 for Zambia Statistics Agency",
    "amount": 43945790.36,
    "currency": "ZMW",
    "status": "Active",
    "preparedBy": "John Phiri",
    "approvedBy": "David Tembo",
    "remarks": "Standard mp-budget-analysis record for Zambia Statistics Agency"
  },
  {
    "id": 12,
    "referenceNumber": "MPBUDGE-ZAMSTATS-2024-012",
    "entity": "Zambia Statistics Agency",
    "date": "2024-12-09T00:00:00Z",
    "description": "Mp Budget Analysis entry 12 for Zambia Statistics Agency",
    "amount": 5217805.09,
    "currency": "ZMW",
    "status": "Active",
    "preparedBy": "Mwanza Simwanza",
    "approvedBy": "Jacqueline Chilufya",
    "remarks": "Standard mp-budget-analysis record for Zambia Statistics Agency"
  },
  {
    "id": 13,
    "referenceNumber": "MPBUDGE-ZAMSTATS-2024-013",
    "entity": "Zambia Statistics Agency",
    "date": "2024-11-17T00:00:00Z",
    "description": "Mp Budget Analysis entry 13 for Zambia Statistics Agency",
    "amount": 9898252.49,
    "currency": "ZMW",
    "status": "Completed",
    "preparedBy": "Jacqueline Banda",
    "approvedBy": "James Lungu",
    "remarks": "Standard mp-budget-analysis record for Zambia Statistics Agency"
  },
  {
    "id": 14,
    "referenceNumber": "MPBUDGE-ZAMSTATS-2024-014",
    "entity": "Zambia Statistics Agency",
    "date": "2024-12-06T00:00:00Z",
    "description": "Mp Budget Analysis entry 14 for Zambia Statistics Agency",
    "amount": 24776054.85,
    "currency": "ZMW",
    "status": "Approved",
    "preparedBy": "Patricia Mvula",
    "approvedBy": "Susan Nsofu",
    "remarks": "Standard mp-budget-analysis record for Zambia Statistics Agency"
  },
  {
    "id": 15,
    "referenceNumber": "MPBUDGE-ZAMSTATS-2024-015",
    "entity": "Zambia Statistics Agency",
    "date": "2024-11-15T00:00:00Z",
    "description": "Mp Budget Analysis entry 15 for Zambia Statistics Agency",
    "amount": 43133838.11,
    "currency": "ZMW",
    "status": "Completed",
    "preparedBy": "Susan Chilufya",
    "approvedBy": "Florence Zulu",
    "remarks": "Standard mp-budget-analysis record for Zambia Statistics Agency"
  },
  {
    "id": 16,
    "referenceNumber": "MPBUDGE-ZAMSTATS-2024-016",
    "entity": "Zambia Statistics Agency",
    "date": "2024-11-13T00:00:00Z",
    "description": "Mp Budget Analysis entry 16 for Zambia Statistics Agency",
    "amount": 46098868.14,
    "currency": "ZMW",
    "status": "Active",
    "preparedBy": "Joseph Kaputa",
    "approvedBy": "Robert Mwanza",
    "remarks": "Standard mp-budget-analysis record for Zambia Statistics Agency"
  },
  {
    "id": 17,
    "referenceNumber": "MPBUDGE-ZAMSTATS-2024-017",
    "entity": "Zambia Statistics Agency",
    "date": "2024-04-14T00:00:00Z",
    "description": "Mp Budget Analysis entry 17 for Zambia Statistics Agency",
    "amount": 20827587.31,
    "currency": "ZMW",
    "status": "Active",
    "preparedBy": "Michael Chilufya",
    "approvedBy": "Christine Nakambwe",
    "remarks": "Standard mp-budget-analysis record for Zambia Statistics Agency"
  },
  {
    "id": 18,
    "referenceNumber": "MPBUDGE-ZAMSTATS-2024-018",
    "entity": "Zambia Statistics Agency",
    "date": "2024-05-02T00:00:00Z",
    "description": "Mp Budget Analysis entry 18 for Zambia Statistics Agency",
    "amount": 19646882.77,
    "currency": "ZMW",
    "status": "Approved",
    "preparedBy": "Miriam Malama",
    "approvedBy": "Francis Ngoma",
    "remarks": "Standard mp-budget-analysis record for Zambia Statistics Agency"
  },
  {
    "id": 19,
    "referenceNumber": "MPBUDGE-ZAMSTATS-2024-019",
    "entity": "Zambia Statistics Agency",
    "date": "2024-07-21T00:00:00Z",
    "description": "Mp Budget Analysis entry 19 for Zambia Statistics Agency",
    "amount": 28919328.79,
    "currency": "ZMW",
    "status": "Completed",
    "preparedBy": "Beatrice Nsofu",
    "approvedBy": "Patricia Mwanza",
    "remarks": "Standard mp-budget-analysis record for Zambia Statistics Agency"
  },
  {
    "id": 20,
    "referenceNumber": "MPBUDGE-ZAMSTATS-2024-020",
    "entity": "Zambia Statistics Agency",
    "date": "2024-07-03T00:00:00Z",
    "description": "Mp Budget Analysis entry 20 for Zambia Statistics Agency",
    "amount": 11873613.99,
    "currency": "ZMW",
    "status": "Pending",
    "preparedBy": "Dorothy Zulu",
    "approvedBy": "David Mwanza",
    "remarks": "Standard mp-budget-analysis record for Zambia Statistics Agency"
  },
  {
    "id": 21,
    "referenceNumber": "MPBUDGE-ZAMSTATS-2024-021",
    "entity": "Zambia Statistics Agency",
    "date": "2024-11-02T00:00:00Z",
    "description": "Mp Budget Analysis entry 21 for Zambia Statistics Agency",
    "amount": 15162682.62,
    "currency": "ZMW",
    "status": "Pending",
    "preparedBy": "Elizabeth Simwanza",
    "approvedBy": "Catherine Ngoma",
    "remarks": "Standard mp-budget-analysis record for Zambia Statistics Agency"
  },
  {
    "id": 22,
    "referenceNumber": "MPBUDGE-ZAMSTATS-2024-022",
    "entity": "Zambia Statistics Agency",
    "date": "2024-02-07T00:00:00Z",
    "description": "Mp Budget Analysis entry 22 for Zambia Statistics Agency",
    "amount": 45957185.57,
    "currency": "ZMW",
    "status": "Completed",
    "preparedBy": "Benjamin Nkonde",
    "approvedBy": "Samuel Tembo",
    "remarks": "Standard mp-budget-analysis record for Zambia Statistics Agency"
  },
  {
    "id": 23,
    "referenceNumber": "MPBUDGE-ZAMSTATS-2024-023",
    "entity": "Zambia Statistics Agency",
    "date": "2024-08-05T00:00:00Z",
    "description": "Mp Budget Analysis entry 23 for Zambia Statistics Agency",
    "amount": 27131591.83,
    "currency": "ZMW",
    "status": "Active",
    "preparedBy": "Miriam Ngoma",
    "approvedBy": "Emmanuel Mwale",
    "remarks": "Standard mp-budget-analysis record for Zambia Statistics Agency"
  },
  {
    "id": 24,
    "referenceNumber": "MPBUDGE-ZAMSTATS-2024-024",
    "entity": "Zambia Statistics Agency",
    "date": "2024-07-24T00:00:00Z",
    "description": "Mp Budget Analysis entry 24 for Zambia Statistics Agency",
    "amount": 5644061.53,
    "currency": "ZMW",
    "status": "Approved",
    "preparedBy": "Charity Kaputa",
    "approvedBy": "Mary Phiri",
    "remarks": "Standard mp-budget-analysis record for Zambia Statistics Agency"
  },
  {
    "id": 25,
    "referenceNumber": "MPBUDGE-ZAMSTATS-2024-025",
    "entity": "Zambia Statistics Agency",
    "date": "2024-06-28T00:00:00Z",
    "description": "Mp Budget Analysis entry 25 for Zambia Statistics Agency",
    "amount": 4001391.07,
    "currency": "ZMW",
    "status": "Pending",
    "preparedBy": "Robert Mwanza",
    "approvedBy": "Benjamin Mutale",
    "remarks": "Standard mp-budget-analysis record for Zambia Statistics Agency"
  }
]