[
  {
    "id": 1,
    "referenceNumber": "WORKFLOW-ZAMSTATS-2024-001",
    "entity": "Zambia Statistics Agency",
    "date": "2024-12-20T00:00:00Z",
    "description": "Workflow Enhancements entry 1 for Zambia Statistics Agency",
    "amount": 23704504.45,
    "currency": "ZMW",
    "status": "Completed",
    "preparedBy": "Robert Chilufya",
    "approvedBy": "Catherine Mutale",
    "remarks": "Standard workflow-enhancements record for Zambia Statistics Agency"
  },
  {
    "id": 2,
    "referenceNumber": "WORKFLOW-ZAMSTATS-2024-002",
    "entity": "Zambia Statistics Agency",
    "date": "2024-08-20T00:00:00Z",
    "description": "Workflow Enhancements entry 2 for Zambia Statistics Agency",
    "amount": 25833413.67,
    "currency": "ZMW",
    "status": "Active",
    "preparedBy": "Alice Nsofu",
    "approvedBy": "Charity Sakala",
    "remarks": "Standard workflow-enhancements record for Zambia Statistics Agency"
  },
  {
    "id": 3,
    "referenceNumber": "WORKFLOW-ZAMSTATS-2024-003",
    "entity": "Zambia Statistics Agency",
    "date": "2024-10-22T00:00:00Z",
    "description": "Workflow Enhancements entry 3 for Zambia Statistics Agency",
    "amount": 29172264.13,
    "currency": "ZMW",
    "status": "Pending",
    "preparedBy": "Michael Banda",
    "approvedBy": "David Sakala",
    "remarks": "Standard workflow-enhancements record for Zambia Statistics Agency"
  },
  {
    "id": 4,
    "referenceNumber": "WORKFLOW-ZAMSTATS-2024-004",
    "entity": "Zambia Statistics Agency",
    "date": "2024-03-05T00:00:00Z",
    "description": "Workflow Enhancements entry 4 for Zambia Statistics Agency",
    "amount": 49164618.08,
    "currency": "ZMW",
    "status": "Active",
    "preparedBy": "Francis Mvula",
    "approvedBy": "Andrew Mbewe",
    "remarks": "Standard workflow-enhancements record for Zambia Statistics Agency"
  },
  {
    "id": 5,
    "referenceNumber": "WORKFLOW-ZAMSTATS-2024-005",
    "entity": "Zambia Statistics Agency",
    "date": "2024-07-15T00:00:00Z",
    "description": "Workflow Enhancements entry 5 for Zambia Statistics Agency",
    "amount": 37955295.0,
    "currency": "ZMW",
    "status": "Active",
    "preparedBy": "James Phiri",
    "approvedBy": "David Chilufya",
    "remarks": "Standard workflow-enhancements record for Zambia Statistics Agency"
  },
  {
    "id": 6,
    "referenceNumber": "WORKFLOW-ZAMSTATS-2024-006",
    "entity": "Zambia Statistics Agency",
    "date": "2024-05-03T00:00:00Z",
    "description": "Workflow Enhancements entry 6 for Zambia Statistics Agency",
    "amount": 3372583.69,
    "currency": "ZMW",
    "status": "Pending",
    "preparedBy": "Andrew Lungu",
    "approvedBy": "Peter Chilufya",
    "remarks": "Standard workflow-enhancements record for Zambia Statistics Agency"
  },
  {
    "id": 7,
    "referenceNumber": "WORKFLOW-ZAMSTATS-2024-007",
    "entity": "Zambia Statistics Agency",
    "date": "2024-04-09T00:00:00Z",
    "description": "Workflow Enhancements entry 7 for Zambia Statistics Agency",
    "amount": 41117257.4,
    "currency": "ZMW",
    "status": "Pending",
    "preparedBy": "Catherine Simukonda",
    "approvedBy": "Andrew Banda",
    "remarks": "Standard workflow-enhancements record for Zambia Statistics Agency"
  },
  {
    "id": 8,
    "referenceNumber": "WORKFLOW-ZAMSTATS-2024-008",
    "entity": "Zambia Statistics Agency",
    "date": "2024-11-19T00:00:00Z",
    "description": "Workflow Enhancements entry 8 for Zambia Statistics Agency",
    "amount": 42094792.84,
    "currency": "ZMW",
    "status": "Completed",
    "preparedBy": "Esther Mvula",
    "approvedBy": "Elizabeth Nakambwe",
    "remarks": "Standard workflow-enhancements record for Zambia Statistics Agency"
  },
  {
    "id": 9,
    "referenceNumber": "WORKFLOW-ZAMSTATS-2024-009",
    "entity": "Zambia Statistics Agency",
    "date": "2024-01-07T00:00:00Z",
    "description": "Workflow Enhancements entry 9 for Zambia Statistics Agency",
    "amount": 17019161.1,
    "currency": "ZMW",
    "status": "Pending",
    "preparedBy": "Elizabeth Mwanza",
    "approvedBy": "Florence Bwalya",
    "remarks": "Standard workflow-enhancements record for Zambia Statistics Agency"
  },
  {
    "id": 10,
    "referenceNumber": "WORKFLOW-ZAMSTATS-2024-010",
    "entity": "Zambia Statistics Agency",
    "date": "2024-03-23T00:00:00Z",
    "description": "Workflow Enhancements entry 10 for Zambia Statistics Agency",
    "amount": 16539882.15,
    "currency": "ZMW",
    "status": "Active",
    "preparedBy": "John Nakambwe",
    "approvedBy": "Patricia Nakambwe",
    "remarks": "Standard workflow-enhancements record for Zambia Statistics Agency"
  },
  {
    "id": 11,
    "referenceNumber": "WORKFLOW-ZAMSTATS-2024-011",
    "entity": "Zambia Statistics Agency",
    "date": "2024-09-06T00:00:00Z",
    "description": "Workflow Enhancements entry 11 for Zambia Statistics Agency",
    "amount": 23758680.01,
    "currency": "ZMW",
    "status": "Active",
    "preparedBy": "Benjamin Mbewe",
    "approvedBy": "Esther Nsofu",
    "remarks": "Standard workflow-enhancements record for Zambia Statistics Agency"
  },
  {
    "id": 12,
    "referenceNumber": "WORKFLOW-ZAMSTATS-2024-012",
    "entity": "Zambia Statistics Agency",
    "date": "2024-06-26T00:00:00Z",
    "description": "Workflow Enhancements entry 12 for Zambia Statistics Agency",
    "amount": 46307085.97,
    "currency": "ZMW",
    "status": "Completed",
    "preparedBy": "Esther Mutale",
    "approvedBy": "Samuel Malama",
    "remarks": "Standard workflow-enhancements record for Zambia Statistics Agency"
  },
  {
    "id": 13,
    "referenceNumber": "WORKFLOW-ZAMSTATS-2024-013",
    "entity": "Zambia Statistics Agency",
    "date": "2024-07-17T00:00:00Z",
    "description": "Workflow Enhancements entry 13 for Zambia Statistics Agency",
    "amount": 30402787.99,
    "currency": "ZMW",
    "status": "Approved",
    "preparedBy": "Emmanuel Mwanza",
    "approvedBy": "Mwanza Mwale",
    "remarks": "Standard workflow-enhancements record for Zambia Statistics Agency"
  },
  {
    "id": 14,
    "referenceNumber": "WORKFLOW-ZAMSTATS-2024-014",
    "entity": "Zambia Statistics Agency",
    "date": "2024-03-25T00:00:00Z",
    "description": "Workflow Enhancements entry 14 for Zambia Statistics Agency",
    "amount": 18890436.72,
    "currency": "ZMW",
    "status": "Approved",
    "preparedBy": "Jacqueline Daka",
    "approvedBy": "Miriam Nkonde",
    "remarks": "Standard workflow-enhancements record for Zambia Statistics Agency"
  },
  {
    "id": 15,
    "referenceNumber": "WORKFLOW-ZAMSTATS-2024-015",
    "entity": "Zambia Statistics Agency",
    "date": "2024-09-20T00:00:00Z",
    "description": "Workflow Enhancements entry 15 for Zambia Statistics Agency",
    "amount": 44565954.08,
    "currency": "ZMW",
    "status": "Completed",
    "preparedBy": "Emmanuel Banda",
    "approvedBy": "Benjamin Nakambwe",
    "remarks": "Standard workflow-enhancements record for Zambia Statistics Agency"
  },
  {
    "id": 16,
    "referenceNumber": "WORKFLOW-ZAMSTATS-2024-016",
    "entity": "Zambia Statistics Agency",
    "date": "2024-02-03T00:00:00Z",
    "description": "Workflow Enhancements entry 16 for Zambia Statistics Agency",
    "amount": 36766375.62,
    "currency": "ZMW",
    "status": "Approved",
    "preparedBy": "Alice Chilufya",
    "approvedBy": "Mary Bwalya",
    "remarks": "Standard workflow-enhancements record for Zambia Statistics Agency"
  },
  {
    "id": 17,
    "referenceNumber": "WORKFLOW-ZAMSTATS-2024-017",
    "entity": "Zambia Statistics Agency",
    "date": "2024-02-25T00:00:00Z",
    "description": "Workflow Enhancements entry 17 for Zambia Statistics Agency",
    "amount": 46458932.36,
    "currency": "ZMW",
    "status": "Pending",
    "preparedBy": "Paul Bwalya",
    "approvedBy": "Elizabeth Mutale",
    "remarks": "Standard workflow-enhancements record for Zambia Statistics Agency"
  },
  {
    "id": 18,
    "referenceNumber": "WORKFLOW-ZAMSTATS-2024-018",
    "entity": "Zambia Statistics Agency",
    "date": "2024-08-12T00:00:00Z",
    "description": "Workflow Enhancements entry 18 for Zambia Statistics Agency",
    "amount": 28877280.54,
    "currency": "ZMW",
    "status": "Approved",
    "preparedBy": "Dorothy Mvula",
    "approvedBy": "Susan Mwanza",
    "remarks": "Standard workflow-enhancements record for Zambia Statistics Agency"
  },
  {
    "id": 19,
    "referenceNumber": "WORKFLOW-ZAMSTATS-2024-019",
    "entity": "Zambia Statistics Agency",
    "date": "2024-10-23T00:00:00Z",
    "description": "Workflow Enhancements entry 19 for Zambia Statistics Agency",
    "amount": 45213336.4,
    "currency": "ZMW",
    "status": "Pending",
    "preparedBy": "Joseph Kaputa",
    "approvedBy": "Paul Zulu",
    "remarks": "Standard workflow-enhancements record for Zambia Statistics Agency"
  },
  {
    "id": 20,
    "referenceNumber": "WORKFLOW-ZAMSTATS-2024-020",
    "entity": "Zambia Statistics Agency",
    "date": "2024-05-03T00:00:00Z",
    "description": "Workflow Enhancements entry 20 for Zambia Statistics Agency",
    "amount": 48158603.0,
    "currency": "ZMW",
    "status": "Active",
    "preparedBy": "Alice Simwanza",
    "approvedBy": "Robert Daka",
    "remarks": "Standard workflow-enhancements record for Zambia Statistics Agency"
  },
  {
    "id": 21,
    "referenceNumber": "WORKFLOW-ZAMSTATS-2024-021",
    "entity": "Zambia Statistics Agency",
    "date": "2024-07-13T00:00:00Z",
    "description": "Workflow Enhancements entry 21 for Zambia Statistics Agency",
    "amount": 16724988.86,
    "currency": "ZMW",
    "status": "Completed",
    "preparedBy": "Alice Mvula",
    "approvedBy": "David Mbewe",
    "remarks": "Standard workflow-enhancements record for Zambia Statistics Agency"
  },
  {
    "id": 22,
    "referenceNumber": "WORKFLOW-ZAMSTATS-2024-022",
    "entity": "Zambia Statistics Agency",
    "date": "2024-11-16T00:00:00Z",
    "description": "Workflow Enhancements entry 22 for Zambia Statistics Agency",
    "amount": 4715005.62,
    "currency": "ZMW",
    "status": "Active",
    "preparedBy": "Susan Lungu",
    "approvedBy": "Florence Chilufya",
    "remarks": "Standard workflow-enhancements record for Zambia Statistics Agency"
  },
  {
    "id": 23,
    "referenceNumber": "WORKFLOW-ZAMSTATS-2024-023",
    "entity": "Zambia Statistics Agency",
    "date": "2024-02-02T00:00:00Z",
    "description": "Workflow Enhancements entry 23 for Zambia Statistics Agency",
    "amount": 49761391.16,
    "currency": "ZMW",
    "status": "Completed",
    "preparedBy": "Elizabeth Mvula",
    "approvedBy": "Elizabeth Sakala",
    "remarks": "Standard workflow-enhancements record for Zambia Statistics Agency"
  },
  {
    "id": 24,
    "referenceNumber": "WORKFLOW-ZAMSTATS-2024-024",
    "entity": "Zambia Statistics Agency",
    "date": "2024-03-11T00:00:00Z",
    "description": "Workflow Enhancements entry 24 for Zambia Statistics Agency",
    "amount": 4583606.75,
    "currency": "ZMW",
    "status": "Pending",
    "preparedBy": "Dorothy Nsofu",
    "approvedBy": "Esther Mvula",
    "remarks": "Standard workflow-enhancements record for Zambia Statistics Agency"
  },
  {
    "id": 25,
    "referenceNumber": "WORKFLOW-ZAMSTATS-2024-025",
    "entity": "Zambia Statistics Agency",
    "date": "2024-01-10T00:00:00Z",
    "description": "Workflow Enhancements entry 25 for Zambia Statistics Agency",
    "amount": 34769272.51,
    "currency": "ZMW",
    "status": "Approved",
    "preparedBy": "Grace Nakambwe",
    "approvedBy": "Elizabeth Bwalya",
    "remarks": "Standard workflow-enhancements record for Zambia Statistics Agency"
  }
]